Metadata-Version: 1.0
Name: SequenceAligner
Version: 0.0.2
Summary: FASTA sequence aligner.
Home-page: https://github.com/Tiffany8/Sequence-Aligner
Author: T Williams
Author-email: trw.visions@gmail.com
License: UNKNOWN
Platform: UNKNOWN
